setup.py
MailMaker/__init__.py
MailMaker/createConfig.py
MailMaker/mailCreator.py
MailMaker.egg-info/PKG-INFO
MailMaker.egg-info/SOURCES.txt
MailMaker.egg-info/dependency_links.txt
MailMaker.egg-info/top_level.txt