Metadata-Version: 1.0
Name: MailMaker
Version: 0.1.5
Summary: MailMaker used to send mails in different applications
Home-page: UNKNOWN
Author: Niklas Maurer
Author-email: UNKNOWN
License: MIT
Keywords: mail,MailMaker,easy mailsending
Platform: UNKNOWN
